[
  {
    "id": "118f6f64d0a4a2c3bd7821822e643ff80b320c77707c2d7d26db43b7ac7b15ce",
    "name": "6cea57c2fb6cbc2a40411135005760f241fffc3e5e67ab99882726431037f908",
    "email": "dpvgxvxbyolumyncrapdcfbaht",
    "age": 32,
    "gender": "Male",
    "city": "815eca977c7d75f72bd23bccc91bc6f9931a42fbf03451eb0d7db8d2a704d94f",
    "country": "USA",
    "salary": 55000,
    "education": "Bachelor's Degree",
    "employment_status": "Employed",
    "department": "Sales",
    "hobby": "Reading",
    "marital_status": "Married",
    "children": 2,
    "years_of_experience": 5,
    "performance_rating": 4.5,
    "last_promotion_date": "2023-05-12",
    "manager": "Jane Smith",
    "work_location": "Office",
    "work_from_home_days": 2,
    "start_date": "hashed_2018-07-15",
    "team_size": 10,
    "working_hours_per_day": 8
  },
  {
    "id": "c2a65649a297b6a31369b5bca9a26b3baffb3db8c7987809443465394e0f7d13",
    "name": "a2dd3acadb1c9dcd956216993056a7f50a9db6e3a16c60b35482139b5349c288",
    "email": "nymnfdbaafvnjgwfokwbqpmpce",
    "age": 28,
    "gender": "Female",
    "city": "8b6e04947230473368190a71c95399a7e9a0c12faa28b04a2dd5a1cc4350a9a9",
    "country": "USA",
    "salary": 60000,
    "education": "Master's Degree",
    "employment_status": "Employed",
    "department": "Marketing",
    "hobby": "Photography",
    "marital_status": "Single",
    "children": 0,
    "years_of_experience": 7,
    "performance_rating": 4.7,
    "last_promotion_date": "2022-11-20",
    "manager": "David Johnson",
    "work_location": "Remote",
    "work_from_home_days": 4,
    "start_date": "hashed_2016-09-20",
    "team_size": 8,
    "working_hours_per_day": 7
  },
  {
    "id": "bff663cf1c8642cfc9820f720240f93d6b244cffecc2b91b168e570aa9763405",
    "name": "19a636ea629a5a125941be060f4af4f475d8b6f6c4766e638f22dfdbaa6fd9f2",
    "email": "rclawugpphighwecqgkwvryvgb",
    "age": 35,
    "gender": "Male",
    "city": "0f5d983d203189bbffc5f686d01f6680bc6a83718a515fe42639347efc92478e",
    "country": "USA",
    "salary": 70000,
    "education": "PhD",
    "employment_status": "Employed",
    "department": "Research & Development",
    "hobby": "Playing Guitar",
    "marital_status": "Married",
    "children": 1,
    "years_of_experience": 10,
    "performance_rating": 4.9,
    "last_promotion_date": "2021-03-10",
    "manager": "Emily Wilson",
    "work_location": "Office",
    "work_from_home_days": 1,
    "start_date": "hashed_2011-08-10",
    "team_size": 15,
    "working_hours_per_day": 8
  }
]